loan_analysis_toolkit/__init__.py
loan_analysis_toolkit/schedule.py
loan_analysis_toolkit/utils.py
loan_analysis_toolkit-0.2.0.dist-info/licenses/LICENSE
loan_analysis_toolkit-0.2.0.dist-info/METADATA
loan_analysis_toolkit-0.2.0.dist-info/WHEEL
loan_analysis_toolkit-0.2.0.dist-info/top_level.txt
loan_analysis_toolkit-0.2.0.dist-info/RECORD
