Metadata-Version: 2.4
Name: loan-analysis-toolkit
Version: 0.2.0
Summary: Provides various tools for loan analysis, including generating loan amortization schedule and total interest paid using daily calculation.
Author-email: Salaken Syed <salaken.buet.eee@gmail.com>
Maintainer-email: Salaken Syed <salaken.buet.eee@gmail.com>
License-Expression: MIT
Project-URL: Homepage, https://github.com/salaken-ds/loan_analysis_toolkit
Project-URL: Issues, https://github.com/salaken-ds/loan_analysis_toolkit/issues
Keywords: amortization,interest schedule,loan analytics,financial strategy,financial education
Classifier: Programming Language :: Python :: 3
Classifier: Operating System :: OS Independent
Classifier: Development Status :: 4 - Beta
Requires-Python: >=3.10
License-File: LICENSE
Requires-Dist: pandas>=2.3.2
Requires-Dist: pydantic>=2.11.9
Dynamic: license-file
